turbobit/__init__.py
turbobit_api-1.0.0.dist-info/LICENSE
turbobit_api-1.0.0.dist-info/METADATA
turbobit_api-1.0.0.dist-info/WHEEL
turbobit_api-1.0.0.dist-info/top_level.txt
turbobit_api-1.0.0.dist-info/RECORD
