Metadata-Version: 2.1
Name: turbobit-api
Version: 1.0.0
Summary: Unofficial python api wrapper from https://turbobit.net/
Home-page: https://github.com/DevCraftClub/TurboBitApi
Author: Maxim Harder
Author-email: dev@devcraft.club
Keywords: api turbobit file video hosting unlimited
Classifier: Programming Language :: Python :: 3
License-File: LICENSE
Requires-Dist: requests
Requires-Dist: python-dotenv
Requires-Dist: python-fsutil
